Metadata-Version: 2.1
Name: power-genai
Version: 1.0
Summary: power genai
Home-page: https://github.com/ExpertOfAI/power_genai
Author: ExpertOfAI
License: MIT
Classifier: Programming Language :: Python :: 3
Classifier: License :: OSI Approved :: MIT License
Classifier: Operating System :: OS Independent
Requires-Python: >=3.6
